eprllib/__init__.py
eprllib/version.py
eprllib/Agents/ActionSpec.py
eprllib/Agents/AgentSpec.py
eprllib/Agents/ObservationSpec.py
eprllib/Agents/__init__.py
eprllib/Agents/Filters/BaseFilter.py
eprllib/Agents/Filters/DefaultFilter.py
eprllib/Agents/Filters/FilterSpec.py
eprllib/Agents/Filters/FullySharedParametersFilter.py
eprllib/Agents/Filters/__init__.py
eprllib/Agents/Rewards/ASHRAE55SimpleModel.py
eprllib/Agents/Rewards/BaseReward.py
eprllib/Agents/Rewards/CEN15251.py
eprllib/Agents/Rewards/EnergyAndAshrae55SimpleModel.py
eprllib/Agents/Rewards/EnergyAndCEN15251.py
eprllib/Agents/Rewards/EnergyRewards.py
eprllib/Agents/Rewards/RewardSpec.py
eprllib/Agents/Rewards/__init__.py
eprllib/Agents/Triggers/BaseTrigger.py
eprllib/Agents/Triggers/ExhaustFanTriggers.py
eprllib/Agents/Triggers/HierarchicalTriggers.py
eprllib/Agents/Triggers/SetpointTriggers.py
eprllib/Agents/Triggers/TriggerSpec.py
eprllib/Agents/Triggers/WindowsOpeningTriggers.py
eprllib/Agents/Triggers/WindowsShadingTriggers.py
eprllib/Agents/Triggers/__init__.py
eprllib/AgentsConnectors/BaseConnector.py
eprllib/AgentsConnectors/CentralizedConnector.py
eprllib/AgentsConnectors/DefaultConnector.py
eprllib/AgentsConnectors/FullySharedParametersConnector.py
eprllib/AgentsConnectors/HierarchicalConnector.py
eprllib/AgentsConnectors/IndependentConnector.py
eprllib/AgentsConnectors/__init__.py
eprllib/Environment/Environment.py
eprllib/Environment/EnvironmentConfig.py
eprllib/Environment/EnvironmentRunner.py
eprllib/Environment/__init__.py
eprllib/Episodes/BaseEpisode.py
eprllib/Episodes/DefaultEpisode.py
eprllib/Episodes/RandomSimpleBuildingEpisode.py
eprllib/Episodes/RandomWeatherEpisode.py
eprllib/Episodes/__init__.py
eprllib/PostProcess/Conventional.py
eprllib/PostProcess/Evaluation.py
eprllib/PostProcess/Plots.py
eprllib/PostProcess/Utils.py
eprllib/PostProcess/__init__.py
eprllib/PostProcess/shap/__init__.py
eprllib/PostProcess/shap/shap_utils.py
eprllib/Utils/__init__.py
eprllib/Utils/agent_utils.py
eprllib-1.6.2.dist-info/METADATA
eprllib-1.6.2.dist-info/WHEEL
eprllib-1.6.2.dist-info/licenses/LICENSE
eprllib-1.6.2.dist-info/RECORD
