Metadata-Version: 2.2
Name: eprllib
Version: 1.6.2
Summary: Building control trought DRL.
Project-URL: Documentation, https://hermmanhender.github.io/eprllib/
Project-URL: GitHub Repository, https://github.com/hermmanhender/eprllib
Project-URL: Bug Tracker, https://github.com/hermmanhender/eprllib/issues
Author: Germán Rodolfo Henderson
License: MIT License
License-File: LICENSE
Classifier: License :: OSI Approved :: MIT License
Classifier: Operating System :: OS Independent
Classifier: Programming Language :: Python :: 3
Requires-Python: >=3.10
Requires-Dist: gymnasium>=0.28.1
Requires-Dist: matplotlib>=3.8.0
Requires-Dist: ray[all]>=2.20.0
Requires-Dist: shap>=0.46.0
Requires-Dist: torch>=2.5.1
